README.rst
setup.py
php_reference/__init__.py
php_reference.egg-info/PKG-INFO
php_reference.egg-info/SOURCES.txt
php_reference.egg-info/dependency_links.txt
php_reference.egg-info/entry_points.txt
php_reference.egg-info/requires.txt
php_reference.egg-info/top_level.txt