Metadata-Version: 1.1
Name: php-reference
Version: 0.0.1
Summary: A CLI command for fetching PHP documentation
Home-page: https://github.com/harto/php-reference
Author: Stuart Campbell
Author-email: stuart@harto.org
License: MIT
Keywords: php reference documentation cli
Platform: UNKNOWN
Classifier: Development Status :: 3 - Alpha
